odoo/addons/web_ir_actions_close_wizard_refresh_view/README.rst
odoo/addons/web_ir_actions_close_wizard_refresh_view/__init__.py
odoo/addons/web_ir_actions_close_wizard_refresh_view/__manifest__.py
odoo/addons/web_ir_actions_close_wizard_refresh_view/i18n/de.po
odoo/addons/web_ir_actions_close_wizard_refresh_view/i18n/it.po
odoo/addons/web_ir_actions_close_wizard_refresh_view/i18n/web_ir_actions_close_wizard_refresh_view.pot
odoo/addons/web_ir_actions_close_wizard_refresh_view/models/__init__.py
odoo/addons/web_ir_actions_close_wizard_refresh_view/models/ir_actions.py
odoo/addons/web_ir_actions_close_wizard_refresh_view/readme/DESCRIPTION.rst
odoo/addons/web_ir_actions_close_wizard_refresh_view/readme/USAGE.rst
odoo/addons/web_ir_actions_close_wizard_refresh_view/security/ir.model.access.csv
odoo/addons/web_ir_actions_close_wizard_refresh_view/static/description/icon.png
odoo/addons/web_ir_actions_close_wizard_refresh_view/static/description/index.html
odoo/addons/web_ir_actions_close_wizard_refresh_view/static/src/js/web_ir_actions_close_wizard_refresh_view.esm.js
odoo_addon_web_ir_actions_close_wizard_refresh_view-16.0.1.0.0.13.dist-info/METADATA
odoo_addon_web_ir_actions_close_wizard_refresh_view-16.0.1.0.0.13.dist-info/WHEEL
odoo_addon_web_ir_actions_close_wizard_refresh_view-16.0.1.0.0.13.dist-info/top_level.txt
odoo_addon_web_ir_actions_close_wizard_refresh_view-16.0.1.0.0.13.dist-info/RECORD
