Metadata-Version: 2.1
Name: odoo-addon-web_ir_actions_close_wizard_refresh_view
Version: 16.0.1.0.0.13
Summary: Allow to refresh view data without reload the page.
Home-page: https://github.com/OCA/web
Author: LevelPrime srl, Nova Code, Odoo Community Association (OCA)
Author-email: support@odoo-community.org
License: AGPL-3
Classifier: Programming Language :: Python
Classifier: Framework :: Odoo
Classifier: Framework :: Odoo :: 16.0
Classifier: License :: OSI Approved :: GNU Affero General Public License v3
Classifier: Development Status :: 4 - Beta
Requires-Python: >=3.10
Requires-Dist: odoo<16.1dev,>=16.0a
